woolworm/__init__.py
woolworm/core.py
woolworm-0.0.10.dist-info/METADATA
woolworm-0.0.10.dist-info/WHEEL
woolworm-0.0.10.dist-info/top_level.txt
woolworm-0.0.10.dist-info/RECORD
