Metadata-Version: 2.4
Name: woolworm
Version: 0.0.10
Summary: Add your description here
Requires-Python: >=3.12
Requires-Dist: loguru>=0.7.3
Requires-Dist: marker-pdf[full]>=1.9.3
Requires-Dist: ollama>=0.5.4
Requires-Dist: opencv-python>=4.12.0.88
Requires-Dist: psutil>=7.1.0
Requires-Dist: pytesseract>=0.3.13
Requires-Dist: scikit-image>=0.25.2
Requires-Dist: scipy>=1.16.2
Requires-Dist: typer<0.17.0
